mylib038/__init__.py
mylib038-0.1.dist-info/LICENSE.txt
mylib038-0.1.dist-info/METADATA
mylib038-0.1.dist-info/WHEEL
mylib038-0.1.dist-info/top_level.txt
mylib038-0.1.dist-info/RECORD
