Metadata-Version: 2.1
Name: mylib038
Version: 0.1
Summary: for calculating square
Author: Nitin
Author-email: shivasagar033@gmail.com
Classifier: Programming Language :: Python :: 3
Classifier: License :: OSI Approved :: MIT License
Classifier: Operating System :: OS Independent
License-File: LICENSE.txt
